{
  "lastUpdated": "2025-10-28T05:37:14.546Z",
  "professors": [
    {
      "id": "1",
      "name": "Prof. Dr. Ir. Ahmad Dahlan, M.T.",
      "title": "Professor",
      "faculty": "Fakultas Teknik",
      "expertise": [
        "Teknik Sipil",
        "Manajemen Konstruksi",
        "Teknologi Beton"
      ],
      "email": "ahmad.dahlan@upnvj.ac.id"
    },
    {
      "id": "2",
      "name": "Dr. Eng. Bambang Suryadi, S.T., M.T.",
      "title": "Associate Professor",
      "faculty": "Fakultas Teknik",
      "expertise": [
        "Teknik Mesin",
        "Termodinamika",
        "Energi Terbarukan"
      ],
      "email": "bambang.suryadi@upnvj.ac.id"
    },
    {
      "id": "3",
      "name": "Dr. Ir. Candra Wijaya, M.T.",
      "title": "Associate Professor",
      "faculty": "Fakultas Teknik",
      "expertise": [
        "Teknik Elektro",
        "Sistem Kontrol",
        "Robotika"
      ],
      "email": "candra.wijaya@upnvj.ac.id"
    },
    {
      "id": "4",
      "name": "Dr. Dwi Hartono, S.T., M.Eng.",
      "title": "Assistant Professor",
      "faculty": "Fakultas Teknik",
      "expertise": [
        "Teknik Industri",
        "Sistem Produksi",
        "Lean Manufacturing"
      ],
      "email": "dwi.hartono@upnvj.ac.id"
    },
    {
      "id": "5",
      "name": "Dr. Eka Permata, S.T., M.T.",
      "title": "Assistant Professor",
      "faculty": "Fakultas Teknik",
      "expertise": [
        "Arsitektur",
        "Desain Sustainable",
        "Urban Planning"
      ],
      "email": "eka.permata@upnvj.ac.id"
    },
    {
      "id": "6",
      "name": "Fitri Andayani, S.T., M.T.",
      "title": "Lecturer",
      "faculty": "Fakultas Teknik",
      "expertise": [
        "Teknik Lingkungan",
        "Pengolahan Air",
        "Waste Management"
      ],
      "email": "fitri.andayani@upnvj.ac.id"
    },
    {
      "id": "7",
      "name": "Gunawan Pratama, S.T., M.T.",
      "title": "Lecturer",
      "faculty": "Fakultas Teknik",
      "expertise": [
        "Geoteknik",
        "Struktur Bangunan",
        "Material Konstruksi"
      ],
      "email": "gunawan.pratama@upnvj.ac.id"
    },
    {
      "id": "8",
      "name": "Hendra Kusuma, S.T., M.T.",
      "title": "Lecturer",
      "faculty": "Fakultas Teknik",
      "expertise": [
        "Teknik Sipil",
        "Hidrolika",
        "Irigasi"
      ],
      "email": "hendra.kusuma@upnvj.ac.id"
    },
    {
      "id": "9",
      "name": "Dr. Siti Aminah, S.E., M.M.",
      "title": "Associate Professor",
      "faculty": "Fakultas Ekonomi dan Bisnis",
      "expertise": [
        "Manajemen Keuangan",
        "Akuntansi",
        "Ekonomi Bisnis"
      ],
      "email": "siti.aminah@upnvj.ac.id"
    },
    {
      "id": "10",
      "name": "Prof. Dr. Indra Wijaya, S.E., M.M.",
      "title": "Professor",
      "faculty": "Fakultas Ekonomi dan Bisnis",
      "expertise": [
        "Manajemen Strategis",
        "Kewirausahaan",
        "Bisnis Digital"
      ],
      "email": "indra.wijaya@upnvj.ac.id"
    },
    {
      "id": "11",
      "name": "Dr. Joko Prasetyo, S.E., M.Ak.",
      "title": "Associate Professor",
      "faculty": "Fakultas Ekonomi dan Bisnis",
      "expertise": [
        "Akuntansi Manajemen",
        "Audit",
        "Perpajakan"
      ],
      "email": "joko.prasetyo@upnvj.ac.id"
    },
    {
      "id": "12",
      "name": "Dr. Kartika Sari, S.E., M.M.",
      "title": "Assistant Professor",
      "faculty": "Fakultas Ekonomi dan Bisnis",
      "expertise": [
        "Manajemen SDM",
        "Organizational Behavior",
        "Leadership"
      ],
      "email": "kartika.sari@upnvj.ac.id"
    },
    {
      "id": "13",
      "name": "Lestari Wulandari, S.E., M.M.",
      "title": "Lecturer",
      "faculty": "Fakultas Ekonomi dan Bisnis",
      "expertise": [
        "Pemasaran Digital",
        "Brand Management",
        "Consumer Behavior"
      ],
      "email": "lestari.wulandari@upnvj.ac.id"
    },
    {
      "id": "14",
      "name": "Maya Sari, S.E., M.E.",
      "title": "Lecturer",
      "faculty": "Fakultas Ekonomi dan Bisnis",
      "expertise": [
        "Ekonomi Makro",
        "Ekonomi Pembangunan",
        "Ekonomi Regional"
      ],
      "email": "maya.sari@upnvj.ac.id"
    },
    {
      "id": "15",
      "name": "Nur Rahman, S.E., M.M.",
      "title": "Lecturer",
      "faculty": "Fakultas Ekonomi dan Bisnis",
      "expertise": [
        "Manajemen Operasi",
        "Supply Chain",
        "Logistics"
      ],
      "email": "nur.rahman@upnvj.ac.id"
    },
    {
      "id": "16",
      "name": "Dr. Budi Santoso, S.Kom., M.T.",
      "title": "Associate Professor",
      "faculty": "Fakultas Ilmu Komputer",
      "expertise": [
        "Artificial Intelligence",
        "Machine Learning",
        "Data Science"
      ],
      "email": "budi.santoso@upnvj.ac.id"
    },
    {
      "id": "17",
      "name": "Dr. Andi Prasetyo, S.Kom., M.Kom.",
      "title": "Associate Professor",
      "faculty": "Fakultas Ilmu Komputer",
      "expertise": [
        "Software Engineering",
        "Web Development",
        "Mobile Apps"
      ],
      "email": "andi.prasetyo@upnvj.ac.id"
    },
    {
      "id": "18",
      "name": "Citra Dewi, S.Kom., M.Kom.",
      "title": "Assistant Professor",
      "faculty": "Fakultas Ilmu Komputer",
      "expertise": [
        "Database Systems",
        "Big Data",
        "Data Mining"
      ],
      "email": "citra.dewi@upnvj.ac.id"
    },
    {
      "id": "19",
      "name": "Denny Kurniawan, S.Kom., M.T.",
      "title": "Lecturer",
      "faculty": "Fakultas Ilmu Komputer",
      "expertise": [
        "Network Security",
        "Cybersecurity",
        "Ethical Hacking"
      ],
      "email": "denny.kurniawan@upnvj.ac.id"
    },
    {
      "id": "20",
      "name": "Eko Wahyudi, S.Kom., M.Kom.",
      "title": "Lecturer",
      "faculty": "Fakultas Ilmu Komputer",
      "expertise": [
        "Game Development",
        "Computer Graphics",
        "UI/UX Design"
      ],
      "email": "eko.wahyudi@upnvj.ac.id"
    },
    {
      "id": "21",
      "name": "Fajar Nugroho, S.Kom., M.T.",
      "title": "Lecturer",
      "faculty": "Fakultas Ilmu Komputer",
      "expertise": [
        "Cloud Computing",
        "DevOps",
        "System Administration"
      ],
      "email": "fajar.nugroho@upnvj.ac.id"
    },
    {
      "id": "22",
      "name": "Dr. Rina Kartika, S.H., M.H.",
      "title": "Associate Professor",
      "faculty": "Fakultas Hukum",
      "expertise": [
        "Hukum Internasional",
        "Hukum Bisnis",
        "HAM"
      ],
      "email": "rina.kartika@upnvj.ac.id"
    },
    {
      "id": "23",
      "name": "Prof. Dr. Agus Salim, S.H., M.H.",
      "title": "Professor",
      "faculty": "Fakultas Hukum",
      "expertise": [
        "Hukum Pidana",
        "Hukum Acara Pidana",
        "Kriminologi"
      ],
      "email": "agus.salim@upnvj.ac.id"
    },
    {
      "id": "24",
      "name": "Dr. Budi Hartono, S.H., M.H.",
      "title": "Assistant Professor",
      "faculty": "Fakultas Hukum",
      "expertise": [
        "Hukum Perdata",
        "Hukum Kontrak",
        "Hukum Keluarga"
      ],
      "email": "budi.hartono@upnvj.ac.id"
    },
    {
      "id": "25",
      "name": "Chandra Kirana, S.H., M.H.",
      "title": "Lecturer",
      "faculty": "Fakultas Hukum",
      "expertise": [
        "Hukum Tata Negara",
        "Hukum Administrasi",
        "Good Governance"
      ],
      "email": "chandra.kirana@upnvj.ac.id"
    },
    {
      "id": "26",
      "name": "Dian Permata, S.H., M.H.",
      "title": "Lecturer",
      "faculty": "Fakultas Hukum",
      "expertise": [
        "Hukum Lingkungan",
        "Hukum Agraria",
        "Hukum Sumber Daya Alam"
      ],
      "email": "dian.permata@upnvj.ac.id"
    },
    {
      "id": "27",
      "name": "Dr. Muhammad Fadli, S.Sos., M.A.",
      "title": "Associate Professor",
      "faculty": "Fakultas Ilmu Sosial dan Politik",
      "expertise": [
        "Hubungan Internasional",
        "Politik Luar Negeri",
        "Diplomasi"
      ],
      "email": "muhammad.fadli@upnvj.ac.id"
    },
    {
      "id": "28",
      "name": "Dr. Ayu Lestari, S.IP., M.A.",
      "title": "Assistant Professor",
      "faculty": "Fakultas Ilmu Sosial dan Politik",
      "expertise": [
        "Ilmu Politik",
        "Demokrasi",
        "Partai Politik"
      ],
      "email": "ayu.lestari@upnvj.ac.id"
    },
    {
      "id": "29",
      "name": "Bima Sakti, S.Sos., M.Si.",
      "title": "Lecturer",
      "faculty": "Fakultas Ilmu Sosial dan Politik",
      "expertise": [
        "Sosiologi",
        "Antropologi",
        "Masyarakat Urban"
      ],
      "email": "bima.sakti@upnvj.ac.id"
    },
    {
      "id": "30",
      "name": "Citra Andini, S.I.Kom., M.A.",
      "title": "Lecturer",
      "faculty": "Fakultas Ilmu Sosial dan Politik",
      "expertise": [
        "Komunikasi Massa",
        "Media Digital",
        "Public Relations"
      ],
      "email": "citra.andini@upnvj.ac.id"
    },
    {
      "id": "31",
      "name": "Dr. dr. Endang Sari, M.Kes.",
      "title": "Associate Professor",
      "faculty": "Fakultas Ilmu Kesehatan",
      "expertise": [
        "Kesehatan Masyarakat",
        "Epidemiologi",
        "Biostatistik"
      ],
      "email": "endang.sari@upnvj.ac.id"
    },
    {
      "id": "32",
      "name": "Fitria Rahma, S.Kep., M.Kep.",
      "title": "Assistant Professor",
      "faculty": "Fakultas Ilmu Kesehatan",
      "expertise": [
        "Keperawatan",
        "Keperawatan Anak",
        "Pediatric Care"
      ],
      "email": "fitria.rahma@upnvj.ac.id"
    },
    {
      "id": "33",
      "name": "Gita Puspita, S.Gz., M.Gizi.",
      "title": "Lecturer",
      "faculty": "Fakultas Ilmu Kesehatan",
      "expertise": [
        "Ilmu Gizi",
        "Nutrisi Klinis",
        "Diet Therapy"
      ],
      "email": "gita.puspita@upnvj.ac.id"
    },
    {
      "id": "prof-1761464589729",
      "name": "asdasdasdasd",
      "title": "asdasd",
      "faculty": "Fakultas Teknik",
      "expertise": [
        "asdasd"
      ],
      "email": "imannnnugraha@gmail.com"
    },
    {
      "id": "prof-1761464623500",
      "name": "Fauzan",
      "title": "Orang Gila",
      "faculty": "Fakultas Teknik",
      "expertise": [
        "Ngopi"
      ],
      "email": "imannnnugraha@gmail.com"
    }
  ],
  "accreditations": [
    {
      "id": "1",
      "program": "Teknik Sipil",
      "level": "S1",
      "accreditor": "BAN-PT",
      "validUntil": "2026-12-31",
      "status": "active"
    },
    {
      "id": "2",
      "program": "Manajemen",
      "level": "S1",
      "accreditor": "BAN-PT",
      "validUntil": "2025-08-15",
      "status": "active"
    },
    {
      "id": "3",
      "program": "Sistem Informasi",
      "level": "S1",
      "accreditor": "BAN-PT",
      "validUntil": "2027-03-20",
      "status": "active"
    },
    {
      "id": "4",
      "program": "Hukum",
      "level": "S1",
      "accreditor": "BAN-PT",
      "validUntil": "2025-11-10",
      "status": "active"
    },
    {
      "id": "5",
      "program": "Hubungan Internasional",
      "level": "S1",
      "accreditor": "BAN-PT",
      "validUntil": "2026-05-25",
      "status": "active"
    },
    {
      "id": "6",
      "program": "Akuntansi",
      "level": "S2",
      "accreditor": "BAN-PT",
      "validUntil": "2025-01-15",
      "status": "active"
    }
  ],
  "students": [
    {
      "faculty": "Fakultas Teknik",
      "totalStudents": 2800,
      "undergraduate": 2450,
      "graduate": 350,
      "postgraduate": 0
    },
    {
      "faculty": "Fakultas Ekonomi dan Bisnis",
      "totalStudents": 3180,
      "undergraduate": 2800,
      "graduate": 380,
      "postgraduate": 0
    },
    {
      "faculty": "Fakultas Ilmu Komputer",
      "totalStudents": 1930,
      "undergraduate": 1750,
      "graduate": 180,
      "postgraduate": 0
    },
    {
      "faculty": "Fakultas Hukum",
      "totalStudents": 1630,
      "undergraduate": 1450,
      "graduate": 180,
      "postgraduate": 0
    },
    {
      "faculty": "Fakultas Ilmu Sosial dan Politik",
      "totalStudents": 1380,
      "undergraduate": 1200,
      "graduate": 180,
      "postgraduate": 0
    },
    {
      "faculty": "Fakultas Ilmu Kesehatan",
      "totalStudents": 970,
      "undergraduate": 850,
      "graduate": 120,
      "postgraduate": 0
    }
  ],
  "assets": [
    {
      "id": "laboratories",
      "name": "Laboratorium",
      "count": 10,
      "icon": "Flask",
      "color": "blue",
      "details": [
        {
          "id": "lab-comp-301",
          "name": "Laboratorium Komputer 301",
          "room": "301",
          "building": "Gedung Kihajar Dewantara",
          "capacity": 40,
          "equipment": [
            "40 Unit PC",
            "Proyektor",
            "AC",
            "Sound System"
          ],
          "description": "Laboratorium komputer untuk praktikum programming dan sistem informasi"
        },
        {
          "id": "lab-comp-302",
          "name": "Laboratorium Komputer 302",
          "room": "302",
          "building": "Gedung Kihajar Dewantara",
          "capacity": 35,
          "equipment": [
            "35 Unit PC",
            "Smart Board",
            "AC"
          ],
          "description": "Laboratorium komputer untuk multimedia dan desain grafis"
        },
        {
          "id": "lab-fisika",
          "name": "Laboratorium Fisika",
          "room": "201",
          "building": "Gedung Teknik",
          "capacity": 30,
          "equipment": [
            "Alat Ukur Fisika",
            "Osiloskop",
            "Generator Sinyal",
            "Multimeter Digital"
          ],
          "description": "Laboratorium untuk praktikum fisika dasar dan terapan"
        },
        {
          "id": "lab-kimia",
          "name": "Laboratorium Kimia",
          "room": "202",
          "building": "Gedung Teknik",
          "capacity": 25,
          "equipment": [
            "Fume Hood",
            "Spektrofotometer",
            "pH Meter",
            "Timbangan Analitik"
          ],
          "description": "Laboratorium untuk praktikum kimia dasar dan analitik"
        },
        {
          "id": "lab-struktur",
          "name": "Laboratorium Struktur & Material",
          "room": "101",
          "building": "Gedung Teknik",
          "capacity": 20,
          "equipment": [
            "Universal Testing Machine",
            "Concrete Mixer",
            "Compression Test"
          ],
          "description": "Laboratorium pengujian kekuatan material konstruksi"
        },
        {
          "id": "lab-akuntansi",
          "name": "Laboratorium Akuntansi",
          "room": "401",
          "building": "Gedung Ekonomi",
          "capacity": 45,
          "equipment": [
            "45 Unit PC",
            "Software Akuntansi",
            "Printer"
          ],
          "description": "Laboratorium praktikum akuntansi dan sistem informasi akuntansi"
        },
        {
          "id": "lab-bahasa",
          "name": "Laboratorium Bahasa",
          "room": "501",
          "building": "Gedung Rektorat",
          "capacity": 60,
          "equipment": [
            "Audio System",
            "Headset",
            "Booth Individual"
          ],
          "description": "Laboratorium untuk pembelajaran bahasa asing"
        },
        {
          "id": "lab-kesehatan",
          "name": "Laboratorium Kesehatan",
          "room": "301",
          "building": "Gedung Kesehatan",
          "capacity": 30,
          "equipment": [
            "Mikroskop",
            "Centrifuge",
            "Autoclave",
            "Incubator"
          ],
          "description": "Laboratorium untuk praktikum ilmu kesehatan dan kedokteran"
        },
        {
          "id": "lab-network",
          "name": "Laboratorium Jaringan",
          "room": "303",
          "building": "Gedung Kihajar Dewantara",
          "capacity": 25,
          "equipment": [
            "Cisco Router",
            "Switch",
            "Server Rack",
            "Network Tools"
          ],
          "description": "Laboratorium untuk praktikum jaringan komputer dan keamanan siber"
        },
        {
          "id": "lab-robotika",
          "name": "Laboratorium Robotika",
          "room": "203",
          "building": "Gedung Teknik",
          "capacity": 20,
          "equipment": [
            "Arduino Kit",
            "3D Printer",
            "Robotic Arms",
            "Sensor Kit"
          ],
          "description": "Laboratorium untuk pengembangan robotika dan IoT"
        }
      ]
    },
    {
      "id": "libraries",
      "name": "Perpustakaan",
      "count": 3,
      "icon": "BookOpen",
      "color": "green",
      "details": [
        {
          "id": "lib-central",
          "name": "Perpustakaan Pusat",
          "room": "Lantai 1-3",
          "building": "Gedung Perpustakaan",
          "capacity": 500,
          "equipment": [
            "50.000+ Buku",
            "E-Journal Access",
            "Study Room",
            "Digital Collection"
          ],
          "description": "Perpustakaan utama dengan koleksi lengkap dan fasilitas modern"
        },
        {
          "id": "lib-faculty",
          "name": "Perpustakaan Fakultas",
          "room": "Lantai 2",
          "building": "Gedung Teknik",
          "capacity": 100,
          "equipment": [
            "5.000+ Buku Teknik",
            "Journal Collection",
            "Reading Area"
          ],
          "description": "Perpustakaan khusus untuk koleksi buku-buku teknik dan sains"
        },
        {
          "id": "lib-digital",
          "name": "Perpustakaan Digital",
          "room": "Lantai 4",
          "building": "Gedung Rektorat",
          "capacity": 80,
          "equipment": [
            "Digital Archive",
            "Computer Access",
            "Research Database"
          ],
          "description": "Perpustakaan digital dengan akses ke database penelitian internasional"
        }
      ]
    },
    {
      "id": "auditoriums",
      "name": "Auditorium",
      "count": 4,
      "icon": "Users",
      "color": "purple",
      "details": [
        {
          "id": "aud-main",
          "name": "Auditorium Utama",
          "room": "Lantai 1",
          "building": "Gedung Auditorium",
          "capacity": 800,
          "equipment": [
            "Sound System Professional",
            "LED Display",
            "AC Central",
            "Stage Lighting"
          ],
          "description": "Auditorium utama untuk acara besar dan wisuda"
        },
        {
          "id": "aud-minor",
          "name": "Auditorium Kecil",
          "room": "Lantai 2",
          "building": "Gedung Auditorium",
          "capacity": 300,
          "equipment": [
            "Audio Visual System",
            "Projector",
            "Microphone Wireless"
          ],
          "description": "Auditorium untuk seminar dan presentasi akademik"
        },
        {
          "id": "aud-outdoor",
          "name": "Amphitheater",
          "room": "Area Terbuka",
          "building": "Taman Kampus",
          "capacity": 200,
          "equipment": [
            "Portable Sound System",
            "Outdoor Seating"
          ],
          "description": "Area outdoor untuk acara santai dan gathering"
        },
        {
          "id": "aud-faculty",
          "name": "Aula Fakultas",
          "room": "Lantai 3",
          "building": "Gedung Ekonomi",
          "capacity": 150,
          "equipment": [
            "Projector",
            "Audio System",
            "AC"
          ],
          "description": "Aula khusus fakultas untuk acara internal"
        }
      ]
    },
    {
      "id": "sports",
      "name": "Fasilitas Olahraga",
      "count": 6,
      "icon": "Trophy",
      "color": "orange",
      "details": [
        {
          "id": "sport-gym",
          "name": "Gymnasium",
          "room": "Hall Utama",
          "building": "Gedung Olahraga",
          "capacity": 1000,
          "equipment": [
            "Lapangan Basket",
            "Lapangan Badminton",
            "Tribun Penonton"
          ],
          "description": "Gymnasium indoor untuk berbagai cabang olahraga"
        },
        {
          "id": "sport-field",
          "name": "Lapangan Sepak Bola",
          "room": "Area Terbuka",
          "building": "Kompleks Olahraga",
          "capacity": 2000,
          "equipment": [
            "Rumput Sintetis",
            "Gawang Standar",
            "Lampu Sorot"
          ],
          "description": "Lapangan sepak bola standar FIFA dengan fasilitas lengkap"
        },
        {
          "id": "sport-tennis",
          "name": "Lapangan Tenis",
          "room": "Court 1-2",
          "building": "Kompleks Olahraga",
          "equipment": [
            "2 Lapangan Hard Court",
            "Net Standar",
            "Lighting System"
          ],
          "description": "Lapangan tenis outdoor dengan standar internasional"
        },
        {
          "id": "sport-pool",
          "name": "Kolam Renang",
          "room": "Pool Area",
          "building": "Gedung Olahraga",
          "capacity": 50,
          "equipment": [
            "25m Pool",
            "Starting Block",
            "Lane Ropes",
            "Filtration System"
          ],
          "description": "Kolam renang semi-olimpik untuk olahraga dan rekreasi"
        },
        {
          "id": "sport-fitness",
          "name": "Fitness Center",
          "room": "Lantai 2",
          "building": "Gedung Olahraga",
          "capacity": 30,
          "equipment": [
            "Cardio Equipment",
            "Weight Training",
            "Yoga Area"
          ],
          "description": "Pusat kebugaran dengan peralatan modern"
        },
        {
          "id": "sport-volleyball",
          "name": "Lapangan Voli",
          "room": "Court A-B",
          "building": "Kompleks Olahraga",
          "equipment": [
            "2 Lapangan Indoor",
            "Net Regulation",
            "Scorer Table"
          ],
          "description": "Lapangan voli indoor dengan fasilitas pertandingan"
        }
      ]
    },
    {
      "id": "facilities",
      "name": "Fasilitas Umum",
      "count": 8,
      "icon": "Building2",
      "color": "indigo",
      "details": [
        {
          "id": "fac-clinic",
          "name": "Klinik Kampus",
          "room": "Lantai 1",
          "building": "Gedung Kesehatan",
          "equipment": [
            "Medical Equipment",
            "Pharmacy",
            "Emergency Room"
          ],
          "description": "Klinik kesehatan untuk civitas akademika"
        },
        {
          "id": "fac-mosque",
          "name": "Masjid Kampus",
          "room": "Lantai 1-2",
          "building": "Masjid Al-Jihad",
          "capacity": 1500,
          "equipment": [
            "Sound System",
            "AC Central",
            "Mihrab",
            "Perpustakaan Islam"
          ],
          "description": "Masjid kampus untuk kegiatan ibadah dan keagamaan"
        },
        {
          "id": "fac-canteen",
          "name": "Kantin Pusat",
          "room": "Lantai 1",
          "building": "Food Court",
          "capacity": 400,
          "equipment": [
            "Food Stalls",
            "Dining Area",
            "ATM Center"
          ],
          "description": "Kantin pusat dengan berbagai pilihan makanan"
        },
        {
          "id": "fac-parking",
          "name": "Parkir Kendaraan",
          "room": "Area Parkir A-D",
          "building": "Kompleks Parkir",
          "capacity": 2000,
          "equipment": [
            "Security System",
            "Lighting",
            "Drainage System"
          ],
          "description": "Area parkir luas untuk kendaraan civitas akademika"
        },
        {
          "id": "fac-bank",
          "name": "Bank Center",
          "room": "Lantai 1",
          "building": "Gedung Rektorat",
          "equipment": [
            "ATM Machines",
            "Banking Services",
            "Money Changer"
          ],
          "description": "Pusat layanan perbankan dalam kampus"
        },
        {
          "id": "fac-wifi",
          "name": "WiFi Hotspot",
          "room": "Seluruh Area",
          "building": "Kampus UPNVJ",
          "equipment": [
            "Fiber Optic Network",
            "Access Points",
            "24/7 Internet"
          ],
          "description": "Jaringan WiFi gratis di seluruh area kampus"
        },
        {
          "id": "fac-garden",
          "name": "Taman Kampus",
          "room": "Area Hijau",
          "building": "Kompleks Taman",
          "equipment": [
            "Gazebo",
            "Jogging Track",
            "Outdoor Seating"
          ],
          "description": "Area hijau untuk relaksasi dan kegiatan outdoor"
        },
        {
          "id": "fac-coop",
          "name": "Koperasi Mahasiswa",
          "room": "Lantai 1",
          "building": "Student Center",
          "equipment": [
            "Mini Market",
            "Stationery Shop",
            "Printing Services"
          ],
          "description": "Koperasi yang menyediakan kebutuhan mahasiswa"
        }
      ]
    }
  ],
  "programs": [
    {
      "id": "ft-s1-teknik-sipil",
      "name": "S1 Teknik Sipil",
      "level": "S1",
      "faculty": "Fakultas Teknik",
      "students": 650,
      "color": "#3B82F6"
    },
    {
      "id": "ft-s1-teknik-mesin",
      "name": "S1 Teknik Mesin",
      "level": "S1",
      "faculty": "Fakultas Teknik",
      "students": 580,
      "color": "#1D4ED8"
    },
    {
      "id": "ft-s1-teknik-elektro",
      "name": "S1 Teknik Elektro",
      "level": "S1",
      "faculty": "Fakultas Teknik",
      "students": 520,
      "color": "#2563EB"
    },
    {
      "id": "ft-s1-teknik-industri",
      "name": "S1 Teknik Industri",
      "level": "S1",
      "faculty": "Fakultas Teknik",
      "students": 480,
      "color": "#1E40AF"
    },
    {
      "id": "ft-s1-arsitektur",
      "name": "S1 Arsitektur",
      "level": "S1",
      "faculty": "Fakultas Teknik",
      "students": 220,
      "color": "#1E3A8A"
    },
    {
      "id": "ft-s2-teknik-sipil",
      "name": "S2 Teknik Sipil",
      "level": "S2",
      "faculty": "Fakultas Teknik",
      "students": 180,
      "color": "#60A5FA"
    },
    {
      "id": "ft-s2-teknik-mesin",
      "name": "S2 Teknik Mesin",
      "level": "S2",
      "faculty": "Fakultas Teknik",
      "students": 120,
      "color": "#93C5FD"
    },
    {
      "id": "ft-s2-arsitektur",
      "name": "S2 Arsitektur",
      "level": "S2",
      "faculty": "Fakultas Teknik",
      "students": 50,
      "color": "#BFDBFE"
    },
    {
      "id": "feb-s1-manajemen",
      "name": "S1 Manajemen",
      "level": "S1",
      "faculty": "Fakultas Ekonomi dan Bisnis",
      "students": 950,
      "color": "#10B981"
    },
    {
      "id": "feb-s1-akuntansi",
      "name": "S1 Akuntansi",
      "level": "S1",
      "faculty": "Fakultas Ekonomi dan Bisnis",
      "students": 840,
      "color": "#059669"
    },
    {
      "id": "feb-s1-ekonomi",
      "name": "S1 Ekonomi Pembangunan",
      "level": "S1",
      "faculty": "Fakultas Ekonomi dan Bisnis",
      "students": 620,
      "color": "#047857"
    },
    {
      "id": "feb-d3-akuntansi",
      "name": "D3 Akuntansi",
      "level": "D3",
      "faculty": "Fakultas Ekonomi dan Bisnis",
      "students": 390,
      "color": "#065F46"
    },
    {
      "id": "feb-s2-manajemen",
      "name": "S2 Manajemen",
      "level": "S2",
      "faculty": "Fakultas Ekonomi dan Bisnis",
      "students": 220,
      "color": "#34D399"
    },
    {
      "id": "feb-s2-akuntansi",
      "name": "S2 Akuntansi",
      "level": "S2",
      "faculty": "Fakultas Ekonomi dan Bisnis",
      "students": 160,
      "color": "#6EE7B7"
    },
    {
      "id": "fik-s1-informatika",
      "name": "S1 Informatika",
      "level": "S1",
      "faculty": "Fakultas Ilmu Komputer",
      "students": 680,
      "color": "#8B5CF6"
    },
    {
      "id": "fik-s1-sistem-informasi",
      "name": "S1 Sistem Informasi",
      "level": "S1",
      "faculty": "Fakultas Ilmu Komputer",
      "students": 620,
      "color": "#7C3AED"
    },
    {
      "id": "fik-s1-teknik-komputer",
      "name": "S1 Teknik Komputer",
      "level": "S1",
      "faculty": "Fakultas Ilmu Komputer",
      "students": 450,
      "color": "#6D28D9"
    },
    {
      "id": "fik-d3-sistem-informasi",
      "name": "D3 Sistem Informasi",
      "level": "D3",
      "faculty": "Fakultas Ilmu Komputer",
      "students": 180,
      "color": "#5B21B6"
    },
    {
      "id": "fik-s2-informatika",
      "name": "S2 Informatika",
      "level": "S2",
      "faculty": "Fakultas Ilmu Komputer",
      "students": 120,
      "color": "#A78BFA"
    },
    {
      "id": "fik-s2-sistem-informasi",
      "name": "S2 Sistem Informasi",
      "level": "S2",
      "faculty": "Fakultas Ilmu Komputer",
      "students": 60,
      "color": "#C4B5FD"
    },
    {
      "id": "fh-s1-hukum",
      "name": "S1 Ilmu Hukum",
      "level": "S1",
      "faculty": "Fakultas Hukum",
      "students": 1450,
      "color": "#F59E0B"
    },
    {
      "id": "fh-s2-hukum",
      "name": "S2 Ilmu Hukum",
      "level": "S2",
      "faculty": "Fakultas Hukum",
      "students": 180,
      "color": "#FBBF24"
    },
    {
      "id": "fisip-s1-hubungan-internasional",
      "name": "S1 Hubungan Internasional",
      "level": "S1",
      "faculty": "Fakultas Ilmu Sosial dan Politik",
      "students": 420,
      "color": "#EF4444"
    },
    {
      "id": "fisip-s1-ilmu-politik",
      "name": "S1 Ilmu Politik",
      "level": "S1",
      "faculty": "Fakultas Ilmu Sosial dan Politik",
      "students": 380,
      "color": "#DC2626"
    },
    {
      "id": "fisip-s1-sosiologi",
      "name": "S1 Sosiologi",
      "level": "S1",
      "faculty": "Fakultas Ilmu Sosial dan Politik",
      "students": 240,
      "color": "#B91C1C"
    },
    {
      "id": "fisip-s1-komunikasi",
      "name": "S1 Ilmu Komunikasi",
      "level": "S1",
      "faculty": "Fakultas Ilmu Sosial dan Politik",
      "students": 160,
      "color": "#991B1B"
    },
    {
      "id": "fisip-s2-hubungan-internasional",
      "name": "S2 Hubungan Internasional",
      "level": "S2",
      "faculty": "Fakultas Ilmu Sosial dan Politik",
      "students": 120,
      "color": "#F87171"
    },
    {
      "id": "fisip-s2-ilmu-politik",
      "name": "S2 Ilmu Politik",
      "level": "S2",
      "faculty": "Fakultas Ilmu Sosial dan Politik",
      "students": 60,
      "color": "#FCA5A5"
    },
    {
      "id": "fikes-s1-keperawatan",
      "name": "S1 Keperawatan",
      "level": "S1",
      "faculty": "Fakultas Ilmu Kesehatan",
      "students": 420,
      "color": "#06B6D4"
    },
    {
      "id": "fikes-s1-gizi",
      "name": "S1 Ilmu Gizi",
      "level": "S1",
      "faculty": "Fakultas Ilmu Kesehatan",
      "students": 280,
      "color": "#0891B2"
    },
    {
      "id": "fikes-s1-kesehatan-masyarakat",
      "name": "S1 Kesehatan Masyarakat",
      "level": "S1",
      "faculty": "Fakultas Ilmu Kesehatan",
      "students": 150,
      "color": "#0E7490"
    },
    {
      "id": "fikes-s2-keperawatan",
      "name": "S2 Keperawatan",
      "level": "S2",
      "faculty": "Fakultas Ilmu Kesehatan",
      "students": 80,
      "color": "#22D3EE"
    },
    {
      "id": "fikes-s2-gizi",
      "name": "S2 Ilmu Gizi",
      "level": "S2",
      "faculty": "Fakultas Ilmu Kesehatan",
      "students": 40,
      "color": "#67E8F9"
    }
  ],
  "departments": [
    {
      "id": "ft-teknik-sipil",
      "name": "Teknik Sipil & Konstruksi",
      "faculty": "Fakultas Teknik",
      "professors": 2,
      "color": "#3B82F6",
      "description": "Fokus pada konstruksi dan infrastruktur"
    },
    {
      "id": "ft-teknik-mesin",
      "name": "Teknik Mesin & Energi",
      "faculty": "Fakultas Teknik",
      "professors": 1,
      "color": "#1D4ED8",
      "description": "Termodinamika dan energi terbarukan"
    },
    {
      "id": "ft-teknik-elektro",
      "name": "Teknik Elektro & Robotika",
      "faculty": "Fakultas Teknik",
      "professors": 1,
      "color": "#2563EB",
      "description": "Sistem kontrol dan robotika"
    },
    {
      "id": "ft-teknik-industri",
      "name": "Teknik Industri & Manufaktur",
      "faculty": "Fakultas Teknik",
      "professors": 1,
      "color": "#1E40AF",
      "description": "Sistem produksi dan lean manufacturing"
    },
    {
      "id": "ft-arsitektur",
      "name": "Arsitektur & Perencanaan",
      "faculty": "Fakultas Teknik",
      "professors": 1,
      "color": "#1E3A8A",
      "description": "Desain sustainable dan urban planning"
    },
    {
      "id": "ft-teknik-lingkungan",
      "name": "Teknik Lingkungan",
      "faculty": "Fakultas Teknik",
      "professors": 2,
      "color": "#60A5FA",
      "description": "Pengolahan air dan waste management"
    },
    {
      "id": "feb-manajemen",
      "name": "Manajemen & Kewirausahaan",
      "faculty": "Fakultas Ekonomi dan Bisnis",
      "professors": 3,
      "color": "#10B981",
      "description": "Manajemen strategis dan bisnis digital"
    },
    {
      "id": "feb-akuntansi",
      "name": "Akuntansi & Keuangan",
      "faculty": "Fakultas Ekonomi dan Bisnis",
      "professors": 2,
      "color": "#059669",
      "description": "Akuntansi manajemen dan keuangan"
    },
    {
      "id": "feb-ekonomi",
      "name": "Ekonomi Pembangunan",
      "faculty": "Fakultas Ekonomi dan Bisnis",
      "professors": 1,
      "color": "#047857",
      "description": "Ekonomi makro dan regional"
    },
    {
      "id": "feb-pemasaran",
      "name": "Pemasaran & SDM",
      "faculty": "Fakultas Ekonomi dan Bisnis",
      "professors": 1,
      "color": "#065F46",
      "description": "Pemasaran digital dan manajemen SDM"
    },
    {
      "id": "fik-ai-data",
      "name": "AI & Data Science",
      "faculty": "Fakultas Ilmu Komputer",
      "professors": 1,
      "color": "#8B5CF6",
      "description": "Artificial intelligence dan machine learning"
    },
    {
      "id": "fik-software",
      "name": "Software Engineering",
      "faculty": "Fakultas Ilmu Komputer",
      "professors": 1,
      "color": "#7C3AED",
      "description": "Pengembangan software dan web"
    },
    {
      "id": "fik-database",
      "name": "Database & Big Data",
      "faculty": "Fakultas Ilmu Komputer",
      "professors": 1,
      "color": "#6D28D9",
      "description": "Sistem database dan data mining"
    },
    {
      "id": "fik-network",
      "name": "Network & Security",
      "faculty": "Fakultas Ilmu Komputer",
      "professors": 1,
      "color": "#5B21B6",
      "description": "Keamanan jaringan dan cybersecurity"
    },
    {
      "id": "fik-multimedia",
      "name": "Multimedia & Game",
      "faculty": "Fakultas Ilmu Komputer",
      "professors": 1,
      "color": "#A78BFA",
      "description": "Game development dan UI/UX"
    },
    {
      "id": "fik-cloud",
      "name": "Cloud Computing",
      "faculty": "Fakultas Ilmu Komputer",
      "professors": 1,
      "color": "#C4B5FD",
      "description": "Cloud computing dan DevOps"
    },
    {
      "id": "fh-hukum-pidana",
      "name": "Hukum Pidana & Kriminologi",
      "faculty": "Fakultas Hukum",
      "professors": 1,
      "color": "#F59E0B",
      "description": "Hukum pidana dan acara pidana"
    },
    {
      "id": "fh-hukum-perdata",
      "name": "Hukum Perdata & Keluarga",
      "faculty": "Fakultas Hukum",
      "professors": 1,
      "color": "#FBBF24",
      "description": "Hukum kontrak dan keluarga"
    },
    {
      "id": "fh-hukum-bisnis",
      "name": "Hukum Bisnis & Internasional",
      "faculty": "Fakultas Hukum",
      "professors": 1,
      "color": "#FCD34D",
      "description": "Hukum bisnis dan internasional"
    },
    {
      "id": "fh-hukum-tata-negara",
      "name": "Hukum Tata Negara",
      "faculty": "Fakultas Hukum",
      "professors": 1,
      "color": "#FDE68A",
      "description": "Hukum administrasi dan good governance"
    },
    {
      "id": "fh-hukum-lingkungan",
      "name": "Hukum Lingkungan",
      "faculty": "Fakultas Hukum",
      "professors": 1,
      "color": "#FEF3C7",
      "description": "Hukum lingkungan dan sumber daya alam"
    },
    {
      "id": "fisip-hubungan-internasional",
      "name": "Hubungan Internasional",
      "faculty": "Fakultas Ilmu Sosial dan Politik",
      "professors": 1,
      "color": "#EF4444",
      "description": "Politik luar negeri dan diplomasi"
    },
    {
      "id": "fisip-ilmu-politik",
      "name": "Ilmu Politik & Demokrasi",
      "faculty": "Fakultas Ilmu Sosial dan Politik",
      "professors": 1,
      "color": "#DC2626",
      "description": "Demokrasi dan partai politik"
    },
    {
      "id": "fisip-sosiologi",
      "name": "Sosiologi & Antropologi",
      "faculty": "Fakultas Ilmu Sosial dan Politik",
      "professors": 1,
      "color": "#B91C1C",
      "description": "Sosiologi dan masyarakat urban"
    },
    {
      "id": "fisip-komunikasi",
      "name": "Ilmu Komunikasi & Media",
      "faculty": "Fakultas Ilmu Sosial dan Politik",
      "professors": 1,
      "color": "#991B1B",
      "description": "Komunikasi massa dan media digital"
    },
    {
      "id": "fikes-kesehatan-masyarakat",
      "name": "Kesehatan Masyarakat",
      "faculty": "Fakultas Ilmu Kesehatan",
      "professors": 1,
      "color": "#06B6D4",
      "description": "Epidemiologi dan biostatistik"
    },
    {
      "id": "fikes-keperawatan",
      "name": "Keperawatan",
      "faculty": "Fakultas Ilmu Kesehatan",
      "professors": 1,
      "color": "#0891B2",
      "description": "Keperawatan anak dan pediatric care"
    },
    {
      "id": "fikes-gizi",
      "name": "Ilmu Gizi & Nutrisi",
      "faculty": "Fakultas Ilmu Kesehatan",
      "professors": 1,
      "color": "#0E7490",
      "description": "Nutrisi klinis dan diet therapy"
    }
  ]
}